traffic_light_control_module/rtl/top.v
module top (
	input wire clk,
	input wire rst_n,
	input wire [3:0] time_slot,
	input wire sensor_car,
	input wire sensor_pedestrian,
	input wire emergency,
	output reg [2:0] light_NS,
	output reg [2:0] light_EW,	//RED: 3'b100, YELLOW: 3'b010, GREEN: 3'b001
	output reg pedestrian_signal
);

localparam IDLE = 3'b000;
localparam NS_GREEN_EW_RED = 3'b001;
localparam NS_YELLOW_EW_RED = 3'b010;
localparam EW_GREEN_NS_RED = 3'b011;
localparam EW_YELLOW_NS_RED = 3'b100;
localparam PEDESTRIAN_CROSSING = 3'b101;
localparam EMERGENCY = 3'b000;

reg [2:0] state, next_state;
reg [3:0] timer;

initial begin
	light_NS = 3'b100;
	light_EW = 3'b100;
	pedestrian_signal = 1'b0;
end

always @(posedge clk or negedge rst_n) begin
	if(!rst_n) begin
		state <= IDLE;
		timer <= 4'h0;
	end else begin
		state <= next_state;
		if (state != next_state) begin
			timer <= 4'h0;
		end else if (timer < time_slot) begin
			timer <= timer + 1'b1;
		end else begin
			timer <= 4'h0;
		end
	end
end

always @(*) begin
	case (state) 
		IDLE: begin
			next_state <= (emergency) ? EMERGENCY : ((sensor_pedestrian) ? PEDESTRIAN_CROSSING : ((sensor_car) ? NS_GREEN_EW_RED : IDLE));
		end
		NS_GREEN_EW_RED: begin
			next_state <= (timer >= time_slot) ? NS_YELLOW_EW_RED : NS_GREEN_EW_RED;
		end
		NS_YELLOW_EW_RED: begin
			next_state <= (timer >= 2'b10) ? EW_GREEN_NS_RED : NS_YELLOW_EW_RED;
		end
		EW_GREEN_NS_RED: begin
			next_state <= (timer >= time_slot) ? EW_YELLOW_NS_RED : EW_GREEN_NS_RED;
		end
		EW_YELLOW_NS_RED: begin
			next_state <= (timer >= 2'b10) ? IDLE : EW_YELLOW_NS_RED;
		end
		PEDESTRIAN_CROSSING: begin
			next_state <= (timer >= time_slot) ? IDLE : PEDESTRIAN_CROSSING;
		end
		EMERGENCY: begin
			next_state <= (emergency) ? EMERGENCY : IDLE;
		end
		default: next_state <= IDLE;
	endcase
end

always @(*) begin
	if(!rst_n) begin
		light_NS <= 3'b100;	//RED
		light_EW <= 3'b100;	//RED;
		pedestrian_signal <= 1'b0;
	end else begin
		case (state)
			NS_GREEN_EW_RED: begin
				light_NS <= 3'b001;	//GREEN;
				light_EW <= 3'b100;
				pedestrian_signal <= 1'b0;
			end
			NS_YELLOW_EW_RED: begin
				light_NS <= 3'b010;
				light_EW <= 3'b100;
				pedestrian_signal <= 1'b0;
			end
			EW_GREEN_NS_RED: begin
				light_NS <= 3'b100;
				light_EW <= 3'b001;
				pedestrian_signal <= 1'b0;
			end
			EW_YELLOW_NS_RED: begin
				light_NS <= 3'b100;
				light_EW <= 3'b010;
				pedestrian_signal <= 1'b0;
			end
			PEDESTRIAN_CROSSING: begin
				light_NS <= 3'b100;
				light_EW <= 3'b100;
				pedestrian_signal <= 1'b1;
			end
			EMERGENCY: begin
				light_NS <= 3'b100;
				light_EW <= 3'b100;
				pedestrian_signal <= 1'b0;
			end
		endcase
	end
end

endmodule

traffic_light_control_module/tb/test_bench.v
`timescale 1ns/1ps
module test_bench;
	reg clk;
    	reg rst_n;
	reg [3:0] time_slot;
	reg sensor_car;
	reg sensor_pedestrian;
	reg emergency;
	wire [2:0] light_NS;
	wire [2:0] light_EW;
	wire pedestrian_signal;

	top dut(.*);

	initial begin
		clk = 0;
		forever #5 clk = ~clk;
	end
	
	task verify;
		input [2:0] exp_light_NS;
		input [2:0] exp_light_EW;
		input exp_pedestrian_signal;
		begin
			$display("At time: %t, rst_n = 1'b%b, time_slot = 4'h%h, sensor_car = 1'b%b,  sensor_pedestrian = 1'b%b, emergency = 1'b%b", $time, rst_n, time_slot, sensor_car, sensor_pedestrian, emergency);
			if( light_NS == exp_light_NS && light_EW === exp_light_EW && pedestrian_signal == exp_pedestrian_signal) begin
				$display("------------------------------------------------------------------------------------------------------------------------");
				$display("PASSED: Expected Light_NS = 3'b%b, Got Light_NS = 3'b%b, Expected Ligh_EW = 3'b%b, Got Light_EW = 3'b%b, Expected pedestrian_signal = 1'b%b, Got pedestrian_signal = 1'b%b", exp_light_NS, light_NS, exp_light_EW, light_EW, exp_pedestrian_signal, pedestrian_signal);
				$display("------------------------------------------------------------------------------------------------------------------------");
			end else begin
				$display("------------------------------------------------------------------------------------------------------------------------");
				$display("FAILED: Expected Light_NS = 3'b%b, Got Light_NS = 3'b%b, Expected Ligh_EW = 3'b%b, Got Light_EW = 3'b%b, Expected pedestrian_signal = 1'b%b, Got pedestrian_signal = 1'b%b", exp_light_NS, light_NS, exp_light_EW, light_EW, exp_pedestrian_signal, pedestrian_signal);
				$display("------------------------------------------------------------------------------------------------------------------------");
			end
		end
	endtask

	initial begin
		$dumpfile("test_bench.vcd");
		$dumpvars(0, test_bench);
	
		$display("---------------------------------------------------------------------------------------------------------------------------------");	
		$display("------------------------------------TESTBENCH FOR TRAFFIC LIGHT CONTROL MODULE---------------------------------------------------");	
		$display("---------------------------------------------------------------------------------------------------------------------------------");

		rst_n = 0;
		time_slot = 3'b100;
		sensor_car = 1;
		sensor_pedestrian = 1;
		emergency = 1;
		@(posedge clk);
		verify(3'b100, 3'b100, 0);

		rst_n = 1;
		time_slot = 3'b100;
		sensor_car = 1;
		sensor_pedestrian = 0;
		emergency = 1;
		repeat(time_slot) @(posedge clk);
		verify(3'b100, 3'b100, 0);

		sensor_car = 0;
		sensor_pedestrian = 1; 
		emergency = 0;
		repeat (time_slot)@(posedge clk);
		verify(3'b100, 3'b100, 1);

		sensor_car = 1;
		sensor_pedestrian = 0;
		repeat (time_slot) @(posedge clk);
		verify(3'b001, 3'b100, 0);
		repeat(time_slot+1) @(posedge clk);
		verify(3'b010, 3'b100, 0);
		repeat(3) @(posedge clk);
		verify(3'b100, 3'b001, 0);
		repeat(time_slot+1) @(posedge clk);
		verify(3'b100, 3'b010, 0);
		
		#100;
		$finish;
	end
endmodule

traffic_light_control_module/sim/test_bench.vcd
$date
	Thu Feb 13 20:31:55 2025
$end
$version
	Icarus Verilog
$end
$timescale
	1ps
$end
$scope module test_bench $end
$var wire 1 ! pedestrian_signal $end
$var wire 3 " light_NS [2:0] $end
$var wire 3 # light_EW [2:0] $end
$var reg 1 $ clk $end
$var reg 1 % emergency $end
$var reg 1 & rst_n $end
$var reg 1 ' sensor_car $end
$var reg 1 ( sensor_pedestrian $end
$var reg 4 ) time_slot [3:0] $end
$scope module dut $end
$var wire 1 $ clk $end
$var wire 1 % emergency $end
$var wire 1 & rst_n $end
$var wire 1 ' sensor_car $end
$var wire 1 ( sensor_pedestrian $end
$var wire 4 * time_slot [3:0] $end
$var parameter 3 + EMERGENCY $end
$var parameter 3 , EW_GREEN_NS_RED $end
$var parameter 3 - EW_YELLOW_NS_RED $end
$var parameter 3 . IDLE $end
$var parameter 3 / NS_GREEN_EW_RED $end
$var parameter 3 0 NS_YELLOW_EW_RED $end
$var parameter 3 1 PEDESTRIAN_CROSSING $end
$var reg 3 2 light_EW [2:0] $end
$var reg 3 3 light_NS [2:0] $end
$var reg 3 4 next_state [2:0] $end
$var reg 1 ! pedestrian_signal $end
$var reg 3 5 state [2:0] $end
$var reg 4 6 timer [3:0] $end
$upscope $end
$scope task verify $end
$var reg 3 7 exp_light_EW [2:0] $end
$var reg 3 8 exp_light_NS [2:0] $end
$var reg 1 9 exp_pedestrian_signal $end
$upscope $end
$upscope $end
$enddefinitions $end
$comment Show the parameter values. $end
$dumpall
b101 1
b10 0
b1 /
b0 .
b100 -
b11 ,
b0 +
$end
#0
$dumpvars
x9
bx 8
bx 7
b0 6
b0 5
b0 4
b100 3
b100 2
b100 *
b100 )
1(
1'
0&
1%
0$
b100 #
b100 "
0!
$end
#5000
b1 6
0(
1&
09
b100 7
b100 8
1$
#10000
0$
#15000
b10 6
1$
#20000
0$
#25000
b11 6
1$
#30000
0$
#35000
b100 6
1$
#40000
0$
#45000
b101 4
b0 6
0%
1(
0'
1$
#50000
0$
#55000
1!
b101 5
1$
#60000
0$
#65000
b1 6
1$
#70000
0$
#75000
b10 6
1$
#80000
0$
#85000
b11 6
0(
1'
19
1$
#90000
0$
#95000
b0 4
b100 6
1$
#100000
0$
#105000
0!
b1 4
b0 6
b0 5
1$
#110000
0$
#115000
b1 "
b1 3
b1 5
1$
#120000
0$
#125000
b1 6
09
b1 8
1$
#130000
0$
#135000
b10 6
1$
#140000
0$
#145000
b11 6
1$
#150000
0$
#155000
b10 4
b100 6
1$
#160000
0$
#165000
b10 "
b10 3
b0 6
b10 5
1$
#170000
0$
#175000
b1 6
b10 8
1$
#180000
0$
#185000
b11 4
b10 6
1$
#190000
0$
#195000
b1 #
b1 2
b100 "
b100 3
b0 6
b11 5
1$
#200000
0$
#205000
b1 6
b1 7
b100 8
1$
#210000
0$
#215000
b10 6
1$
#220000
0$
#225000
b11 6
1$
#230000
0$
#235000
b100 4
b100 6
1$
#240000
0$
#245000
b10 #
b10 2
b0 6
b100 5
1$
#250000
0$
#255000
b1 6
b10 7
1$
#260000
0$
#265000
b0 4
b10 6
1$
#270000
0$
#275000
b100 #
b100 2
b1 4
b0 6
b0 5
1$
#280000
0$
#285000
b1 "
b1 3
b1 5
1$
#290000
0$
#295000
b1 6
1$
#300000
0$
#305000
b10 6
1$
#310000
0$
#315000
b11 6
1$
#320000
0$
#325000
b10 4
b100 6
1$
#330000
0$
#335000
b10 "
b10 3
b0 6
b10 5
1$
#340000
0$
#345000
b1 6
1$
#350000
0$
#355000
b11 4
b10 6
1$
